SampleTestLibrary.py
SampleTestLibrary-0.0.2.dist-info/LICENSE
SampleTestLibrary-0.0.2.dist-info/METADATA
SampleTestLibrary-0.0.2.dist-info/WHEEL
SampleTestLibrary-0.0.2.dist-info/top_level.txt
SampleTestLibrary-0.0.2.dist-info/RECORD
