Metadata-Version: 2.1
Name: SampleTestLibrary
Version: 0.0.2
Summary: Samle python package just for practise.....
Author: Ashutosh Bairagi
Classifier: Programming Language :: Python :: 3
Classifier: License :: OSI Approved :: MIT License
Classifier: Operating System :: OS Independent
Requires-Python: >=3.6
License-File: LICENSE
